hardware/RTL/adder.v
`timescale 1ns / 1ps

module adder #(parameter ADDER_SIZE=64)(
    input  wire         clk,
    input  wire         resetn,
    input  wire         start,
    input  wire         subtract,
    input  wire [512:0] in_a,
    input  wire [512:0] in_b,
    output wire [513:0] result,
    output wire         done    
    );
    localparam [2:0]    STATE_IDLE  = 3'b000,//waiting for start
                        STATE_ONE   = 3'b001,//load inputs
                        STATE_TWO   = 3'b010,//add 
                        STATE_THREE = 3'b011;//done 
    reg [511:0] reg_result;
    reg [511:0] operand_a;
    reg [511:0] operand_b;
    wire [ADDER_SIZE:0] add_result;
    wire mux_sel;
    wire [511:0] op_b_sel;

    wire [1:0]hack;
    reg carry;
    wire [511:0] shifted;
    wire end_carry;
    assign op_b_sel=(subtract==1'b1) ? (~in_b):in_b;
    assign mux_sel=(state==STATE_ONE) ? 1'b1:1'b0;// 1 selects input 0 selects shifted
    assign done=(state==STATE_THREE) ? 1'b1 :1'b0;// 1 selects shifted resuld 0 selects add result
    assign end_carry= (subtract==1'b1) ? carry^1:carry;
    assign hack=in_a[512]+in_b[512]+(end_carry); 
    assign shifted=reg_result>>ADDER_SIZE;
    always @(posedge clk) begin
        if (resetn==1'b0 )begin
            reg_result <= 0;
	        operand_a <=0;
            operand_b <=0;
            carry <=0;
        end
        else begin
            operand_a<= (mux_sel==1'b1)? in_a:operand_a>>ADDER_SIZE; 		
            operand_b<= (mux_sel==1'b1)? op_b_sel:operand_b>>ADDER_SIZE; 
            reg_result <= {add_result[ADDER_SIZE-1:0],shifted[512-1-ADDER_SIZE:0]};
            carry <= (state==STATE_ONE) ? subtract:add_result[ADDER_SIZE];
	    if(state==STATE_THREE)
	    	$display("result %0x ",result);
        end
    end  		
    assign result = {hack[1:0],reg_result};
    assign add_result = ( operand_a[ADDER_SIZE-1:0]+operand_b[ADDER_SIZE-1:0]+carry);//save power

                    
    reg  [7:0] cnt;         //3-bit register
    reg  [2:0] state;       //3-bit register
    reg  [2:0] next_state;  //3-bit wire
                        //Sequential Counter logi
    always @(posedge clk)    begin
	if(next_state>=STATE_TWO && next_state<=STATE_THREE)
            begin
                   cnt <= cnt +1;
            end
	else
		cnt <= 0;
    end 
    
    always @(*) 
             begin
                  case (state)
                       STATE_IDLE:
                           begin
                               next_state <= (start==1'b1) ? STATE_ONE:STATE_IDLE;
                           end
                       STATE_ONE:
                           begin
                               next_state <= STATE_TWO;
                           end
                       STATE_TWO:
                            begin
                                next_state <= (cnt<((512/ADDER_SIZE)))?  STATE_TWO:STATE_THREE;//?latch 
                            end
                       STATE_THREE:
                            begin
                                next_state <=  STATE_IDLE; 
                            end
                       default: 
                           begin
                              next_state <= STATE_IDLE;
                           end
                  endcase
             end                             
    
       //Synchronous logic to update state
     always @(posedge clk)
     begin
         if (resetn==1'b0)
         begin
             state <= 0;
         end
         else
         begin
             state <= next_state;
         end
     end
     
 
endmodule

hardware/tb/tb_adder.v

`timescale 1ns / 1ps

/*
Assignment:
1. Use this testbench (tb) to verify the correctness of your adder
    You can start the simulation by pressing the buttons on the left-hand: Simulation | Run Simulation
2. Implement a multi-precision adder in adder.v
3. Update the design with a two's-compliment subtractor (activate it with the 'subtract' wire)
3. Make an implementation of your design (Implementation | Run Implementation).
4. Determine the maximum clock frequency of the design (Efficient designs have a clock of around 100MHz)
5. Calculate the total execution time of one add operation
*/

`timescale 1ns / 1ps
`include "RTL/adder.v"
`define RESET_TIME 25
`define CLK_PERIOD 10
`define CLK_HALF 5

module tb_adder();

    reg          clk;
    reg          resetn;
    reg  [512:0] in_a;
    reg  [512:0] in_b;
    reg          start;
    reg          subtract;
    reg          result_ok;
    wire [513:0] result;
    wire         done;

    adder dut (
        .clk      (clk     ),
        .resetn   (resetn  ),
        .start    (start   ),
        .subtract (subtract),
        .in_a     (in_a    ),
        .in_b     (in_b    ),
        .result   (result  ),
        .done     (done    ));

    // Generate Clock
    initial begin
        clk = 0;
        forever #`CLK_HALF clk = ~clk;
    end

    // Initialize signals to zero
    initial begin
        in_a <= 0;
        in_b <= 0;
        subtract <= 0;
        start <= 0;
    end

    // Reset the circuit
    initial begin
        resetn = 0;
        #`RESET_TIME
        resetn = 1;
    end

    task perform_add;
        input [512:0] a;
        input [512:0] b;
        begin
            in_a <= a;
            in_b <= b;
            start <= 1'd1;
            subtract <= 1'd0;
            #`CLK_PERIOD;
            start <= 1'd0;
            wait (done==1);
            #`CLK_PERIOD;
        end
    endtask

    task perform_sub;
        input [512:0] a;
        input [512:0] b;
        begin
            in_a <= a;
            in_b <= b;
            start <= 1'd1;
            subtract <= 1'd1;
            #`CLK_PERIOD;
            start <= 1'd0;
            wait (done==1);
            #`CLK_PERIOD;
        end
    endtask

    initial begin
    $dumpfile("adder.vcd");
    $dumpvars;
    #`RESET_TIME

    /*************TEST ADDITION*************/
    // Check if 1+1=2
    #`CLK_PERIOD;
    perform_add(513'h1, 513'h1);
    wait (done==1);
    result_ok = (result==514'h2);

    $display("result ok first add=",result_ok);
    //Test addition with large test vectors. You can generate your own with the magma online calculator
    perform_add(513'h1d7dc5a16218f714565bc7a83ea20e4c0ecb7f8226e9dae7fdaeab517d4449c268af0a34ff2402e74a3a1350d45dc36e1ca7beb4e541105a58c3990be06f30aa9,
                513'h1f30aa08f81b00a1ee9e7d3af7cc01dba81837e2ea4a9ad9fea14343dbbd95eb2a6c44aef080d3dc83efeb5e474699aa9dbed2f56c4a26796bf7b209b7c9491a8);
    wait (done==1);//this is a TRAP, don't use for debug 
     result_ok = (result==514'h3cae6faa5a33f7b644fa44e3366e1027b6e3b765113475c1fc4fee955901dfad931b4ee3efa4d6c3ce29feaf1ba45d18ba6691aa518b36d3c4bb4b15983879c51);
    $display("result ok second add=",result_ok);
#1300;/*

    /*************TEST SUBTRACTION*************/
    //Check if 1-1=0
$display("SUBTRACTION");
    #`CLK_PERIOD;
    #`CLK_PERIOD;
    #`CLK_PERIOD;
    perform_sub(513'h1, 513'h1);
    wait (done==1);
    result_ok = (result==514'h0);
    $display("result ok first subtraction=",result_ok);

    //Test subtraction with large test vectors. You can generate your own with the magma online calculator
    perform_sub(513'h17fcaaf8fe3fd0ee41050d74d78c6087b359fc7813e749a65c4981218f36b4da932ce6e09aa0d31ad9fdddd3abd5114a71b7fd733bbca0f2261ddb7d286cf6ee1,
                513'h1f9a0c360f98cb4e0bdac0d74ee9af59daada1a769b5b2b91a54bb6a5790da2da28b78cc2d14a3f513da8adaef1e148e3a9eaecc4ca7a211bed70da87129fb6c6);
    wait (done==1);
    result_ok = (result==514'h78629ec2eea705a0352a4c9d88a2b12dd8ac5ad0aa3196ed41f4c5b737a5daacf0a16e146d8c2f25c62352f8bcb6fcbc37194ea6ef14fee06746cdd4b742fb81b);

    $display("result ok second subtraction=",result_ok);
    $finish;

    end

endmodule

hardware/adder.vcd
$date
	Sun Oct 22 15:27:24 2017
$end
$version
	Icarus Verilog
$end
$timescale
	1ps
$end
$scope module tb_adder $end
$var wire 1 ! done $end
$var wire 514 " result [513:0] $end
$var reg 1 # clk $end
$var reg 513 $ in_a [512:0] $end
$var reg 513 % in_b [512:0] $end
$var reg 1 & resetn $end
$var reg 1 ' result_ok $end
$var reg 1 ( start $end
$var reg 1 ) subtract $end
$scope module dut $end
$var wire 65 * add_result [64:0] $end
$var wire 1 + clk $end
$var wire 1 ! done $end
$var wire 1 , end_carry $end
$var wire 2 - hack [1:0] $end
$var wire 513 . in_a [512:0] $end
$var wire 513 / in_b [512:0] $end
$var wire 1 0 mux_sel $end
$var wire 512 1 op_b_sel [511:0] $end
$var wire 1 2 resetn $end
$var wire 514 3 result [513:0] $end
$var wire 512 4 shifted [511:0] $end
$var wire 1 5 start $end
$var wire 1 6 subtract $end
$var reg 1 7 carry $end
$var reg 8 8 cnt [7:0] $end
$var reg 3 9 next_state [2:0] $end
$var reg 512 : operand_a [511:0] $end
$var reg 512 ; operand_b [511:0] $end
$var reg 512 < reg_result [511:0] $end
$var reg 3 = state [2:0] $end
$upscope $end
$scope task perform_add $end
$var reg 513 > a [512:0] $end
$var reg 513 ? b [512:0] $end
$upscope $end
$scope task perform_sub $end
$var reg 513 @ a [512:0] $end
$var reg 513 A b [512:0] $end
$upscope $end
$upscope $end
$enddefinitions $end
#0
$dumpvars
bx A
bx @
bx ?
bx >
bx =
bx <
bx ;
bx :
b0 9
bx 8
x7
06
05
b0xxxxxxxxxxxxxxxxxxxxxxxxxxxxxxxxxxxxxxxxxxxxxxxxxxxxxxxxxxxxxxxxxxxxxxxxxxxxxxxxxxxxxxxxxxxxxxxxxxxxxxxxxxxxxxxxxxxxxxxxxxxxxxxxxxxxxxxxxxxxxxxxxxxxxxxxxxxxxxxxxxxxxxxxxxxxxxxxxxxxxxxxxxxxxxxxxxxxxxxxxxxxxxxxxxxxxxxxxxxxxxxxxxxxxxxxxxxxxxxxxxxxxxxxxxxxxxxxxxxxxxxxxxxxxxxxxxxxxxxxxxxxxxxxxxxxxxxxxxxxxxxxxxxxxxxxxxxxxxxxxxxxxxxxxxxxxxxxxxxxxxxxxxxxxxxxxxxxxxxxxxxxxxxxxxxxxxxxxxxxxxxxxxxxxxxxxxxxxxxxxxxxxxxxxxxxxxxxxxxxxxxxxxxxxxxxxxxxxxxxxxxxxxxx 4
bx 3
02
b0 1
x0
b0 /
b0 .
bx -
x,
0+
bx *
0)
0(
x'
0&
b0 %
b0 $
0#
bx "
x!
$end
#5000
b0 -
0,
b0 *
b0 4
00
0!
07
b0 ;
b0 :
b0 <
b0 "
b0 3
b0 8
b0 =
1#
1+
#10000
0#
0+
#15000
1#
1+
#20000
0#
0+
#25000
1#
1+
1&
12
#30000
0#
0+
#35000
b1 9
b1 1
1(
15
b1 %
b1 /
b1 $
b1 .
1#
1+
b1 ?
b1 >
#40000
0#
0+
#45000
b10 9
10
b1 =
0(
05
1#
1+
#50000
0#
0+
#55000
00
b10 *
b10 =
b1 8
b1 ;
b1 :
1#
1+
#60000
0#
0+
#65000
b10000000000000000000000000000000000000000000000000000000000000000000000000000000000000000000000000000000000000000000000000000000000000000000000000000000000000000000000000000000000000000000000000000000000000000000000000000000000000000000000000000000000000000000000000000000000000000000000000000000000000000000000000000000000000000000000000000000000000000000000000000000000000000000000000 4
b0 *
b100000000000000000000000000000000000000000000000000000000000000000000000000000000000000000000000000000000000000000000000000000000000000000000000000000000000000000000000000000000000000000000000000000000000000000000000000000000000000000000000000000000000000000000000000000000000000000000000000000000000000000000000000000000000000000000000000000000000000000000000000000000000000000000000000000000000000000000000000000000000000000000000000000000000000000 <
b100000000000000000000000000000000000000000000000000000000000000000000000000000000000000000000000000000000000000000000000000000000000000000000000000000000000000000000000000000000000000000000000000000000000000000000000000000000000000000000000000000000000000000000000000000000000000000000000000000000000000000000000000000000000000000000000000000000000000000000000000000000000000000000000000000000000000000000000000000000000000000000000000000000000000000 "
b100000000000000000000000000000000000000000000000000000000000000000000000000000000000000000000000000000000000000000000000000000000000000000000000000000000000000000000000000000000000000000000000000000000000000000000000000000000000000000000000000000000000000000000000000000000000000000000000000000000000000000000000000000000000000000000000000000000000000000000000000000000000000000000000000000000000000000000000000000000000000000000000000000000000000000 3
b0 ;
b0 :
b10 8
1#
1+
#70000
0#
0+
#75000
b1000000000000000000000000000000000000000000000000000000000000000000000000000000000000000000000000000000000000000000000000000000000000000000000000000000000000000000000000000000000000000000000000000000000000000000000000000000000000000000000000000000000000000000000000000000000000000000000000000000000000000000000000000000000 4
b11 8
b10000000000000000000000000000000000000000000000000000000000000000000000000000000000000000000000000000000000000000000000000000000000000000000000000000000000000000000000000000000000000000000000000000000000000000000000000000000000000000000000000000000000000000000000000000000000000000000000000000000000000000000000000000000000000000000000000000000000000000000000000000000000000000000000000 <
b10000000000000000000000000000000000000000000000000000000000000000000000000000000000000000000000000000000000000000000000000000000000000000000000000000000000000000000000000000000000000000000000000000000000000000000000000000000000000000000000000000000000000000000000000000000000000000000000000000000000000000000000000000000000000000000000000000000000000000000000000000000000000000000000000 "
b10000000000000000000000000000000000000000000000000000000000000000000000000000000000000000000000000000000000000000000000000000000000000000000000000000000000000000000000000000000000000000000000000000000000000000000000000000000000000000000000000000000000000000000000000000000000000000000000000000000000000000000000000000000000000000000000000000000000000000000000000000000000000000000000000 3
1#
1+
#80000
0#
0+
#85000
b100000000000000000000000000000000000000000000000000000000000000000000000000000000000000000000000000000000000000000000000000000000000000000000000000000000000000000000000000000000000000000000000000000000000000000000000000000000000000000000000000000000000000000 4
b1000000000000000000000000000000000000000000000000000000000000000000000000000000000000000000000000000000000000000000000000000000000000000000000000000000000000000000000000000000000000000000000000000000000000000000000000000000000000000000000000000000000000000000000000000000000000000000000000000000000000000000000000000000000 <
b1000000000000000000000000000000000000000000000000000000000000000000000000000000000000000000000000000000000000000000000000000000000000000000000000000000000000000000000000000000000000000000000000000000000000000000000000000000000000000000000000000000000000000000000000000000000000000000000000000000000000000000000000000000000 "
b1000000000000000000000000000000000000000000000000000000000000000000000000000000000000000000000000000000000000000000000000000000000000000000000000000000000000000000000000000000000000000000000000000000000000000000000000000000000000000000000000000000000000000000000000000000000000000000000000000000000000000000000000000000000 3
b100 8
1#
1+
#90000
0#
0+
#95000
b10000000000000000000000000000000000000000000000000000000000000000000000000000000000000000000000000000000000000000000000000000000000000000000000000000000000000000000000000000000000000000000000000 4
b101 8
b100000000000000000000000000000000000000000000000000000000000000000000000000000000000000000000000000000000000000000000000000000000000000000000000000000000000000000000000000000000000000000000000000000000000000000000000000000000000000000000000000000000000000000 <
b100000000000000000000000000000000000000000000000000000000000000000000000000000000000000000000000000000000000000000000000000000000000000000000000000000000000000000000000000000000000000000000000000000000000000000000000000000000000000000000000000000000000000000 "
b100000000000000000000000000000000000000000000000000000000000000000000000000000000000000000000000000000000000000000000000000000000000000000000000000000000000000000000000000000000000000000000000000000000000000000000000000000000000000000000000000000000000000000 3
1#
1+
#100000
0#
0+
#105000
b1000000000000000000000000000000000000000000000000000000000000000000000000000000000000000000000000000000000000000000000000000000000 4
b10000000000000000000000000000000000000000000000000000000000000000000000000000000000000000000000000000000000000000000000000000000000000000000000000000000000000000000000000000000000000000000000000 <
b10000000000000000000000000000000000000000000000000000000000000000000000000000000000000000000000000000000000000000000000000000000000000000000000000000000000000000000000000000000000000000000000000 "
b10000000000000000000000000000000000000000000000000000000000000000000000000000000000000000000000000000000000000000000000000000000000000000000000000000000000000000000000000000000000000000000000000 3
b110 8
1#
1+
#110000
0#
0+
#115000
b100000000000000000000000000000000000000000000000000000000000000000 4
b111 8
b1000000000000000000000000000000000000000000000000000000000000000000000000000000000000000000000000000000000000000000000000000000000 <
b1000000000000000000000000000000000000000000000000000000000000000000000000000000000000000000000000000000000000000000000000000000000 "
b1000000000000000000000000000000000000000000000000000000000000000000000000000000000000000000000000000000000000000000000000000000000 3
1#
1+
#120000
0#
0+
#125000
b11 9
b10 4
b100000000000000000000000000000000000000000000000000000000000000000 <
b100000000000000000000000000000000000000000000000000000000000000000 "
b100000000000000000000000000000000000000000000000000000000000000000 3
b1000 8
1#
1+
#130000
0#
0+
#135000
b0 9
1!
b0 4
b11 =
b1001 8
b10 <
b10 "
b10 3
1#
1+
#140000
0#
0+
#145000
b1 9
b11110011000010101010000010001111100000011011000000001010000111101110100111100111110100111010111101111100110000000001110110111010100000011000001101111110001011101010010010101001101011011001111111101010000101000011010000111101101110111101100101011110101100101010011011000100010010101110111100001000000011010011110111001000001111101111111010110101111001000111010001101001100110101010100111011011111011010010111101010110110001001010001001100111100101101011111101111011001000001001101101111100100101001001000110101000 1
0!
b10 -
b0 <
b1000000000000000000000000000000000000000000000000000000000000000000000000000000000000000000000000000000000000000000000000000000000000000000000000000000000000000000000000000000000000000000000000000000000000000000000000000000000000000000000000000000000000000000000000000000000000000000000000000000000000000000000000000000000000000000000000000000000000000000000000000000000000000000000000000000000000000000000000000000000000000000000000000000000000000000000000000000000000000000000000000000000000000000000000000000000 "
b1000000000000000000000000000000000000000000000000000000000000000000000000000000000000000000000000000000000000000000000000000000000000000000000000000000000000000000000000000000000000000000000000000000000000000000000000000000000000000000000000000000000000000000000000000000000000000000000000000000000000000000000000000000000000000000000000000000000000000000000000000000000000000000000000000000000000000000000000000000000000000000000000000000000000000000000000000000000000000000000000000000000000000000000000000000000 3
b0 8
b0 =
1(
15
b111110011000010101010000010001111100000011011000000001010000111101110100111100111110100111010111101111100110000000001110110111010100000011000001101111110001011101010010010101001101011011001111111101010000101000011010000111101101110111101100101011110101100101010011011000100010010101110111100001000000011010011110111001000001111101111111010110101111001000111010001101001100110101010100111011011111011010010111101010110110001001010001001100111100101101011111101111011001000001001101101111100100101001001000110101000 %
b111110011000010101010000010001111100000011011000000001010000111101110100111100111110100111010111101111100110000000001110110111010100000011000001101111110001011101010010010101001101011011001111111101010000101000011010000111101101110111101100101011110101100101010011011000100010010101110111100001000000011010011110111001000001111101111111010110101111001000111010001101001100110101010100111011011111011010010111101010110110001001010001001100111100101101011111101111011001000001001101101111100100101001001000110101000 /
b111010111110111000101101000010110001000011000111101110001010001010110010110111100011110101000001111101010001000001110010011000000111011001011011111111000001000100110111010011101101011100111111111011010111010101011010100010111110101000100010010011100001001101000101011110000101000110100111111110010010000000010111001110100101000111010000100110101000011010100010111011100001101101110000111001010011110111110101101001110010101000001000100000101101001011000110000111001100100001011111000000110111100110000101010101001 $
b111010111110111000101101000010110001000011000111101110001010001010110010110111100011110101000001111101010001000001110010011000000111011001011011111111000001000100110111010011101101011100111111111011010111010101011010100010111110101000100010010011100001001101000101011110000101000110100111111110010010000000010111001110100101000111010000100110101000011010100010111011100001101101110000111001010011110111110101101001110010101000001000100000101101001011000110000111001100100001011111000000110111100110000101010101001 .
1#
1+
b111110011000010101010000010001111100000011011000000001010000111101110100111100111110100111010111101111100110000000001110110111010100000011000001101111110001011101010010010101001101011011001111111101010000101000011010000111101101110111101100101011110101100101010011011000100010010101110111100001000000011010011110111001000001111101111111010110101111001000111010001101001100110101010100111011011111011010010111101010110110001001010001001100111100101101011111101111011001000001001101101111100100101001001000110101000 ?
b111010111110111000101101000010110001000011000111101110001010001010110010110111100011110101000001111101010001000001110010011000000111011001011011111111000001000100110111010011101101011100111111111011010111010101011010100010111110101000100010010011100001001101000101011110000101000110100111111110010010000000010111001110100101000111010000100110101000011010100010111011100001101101110000111001010011110111110101101001110010101000001000100000101101001011000110000111001100100001011111000000110111100110000101010101001 >
1'
#150000
0#
0+
#155000
b10 9
10
b1 =
0(
05
1#
1+
#160000
0#
0+
#165000
b10100101110110100101100010101100110000011100001111001110001010001 *
00
b11110011000010101010000010001111100000011011000000001010000111101110100111100111110100111010111101111100110000000001110110111010100000011000001101111110001011101010010010101001101011011001111111101010000101000011010000111101101110111101100101011110101100101010011011000100010010101110111100001000000011010011110111001000001111101111111010110101111001000111010001101001100110101010100111011011111011010010111101010110110001001010001001100111100101101011111101111011001000001001101101111100100101001001000110101000 ;
b11010111110111000101101000010110001000011000111101110001010001010110010110111100011110101000001111101010001000001110010011000000111011001011011111111000001000100110111010011101101011100111111111011010111010101011010100010111110101000100010010011100001001101000101011110000101000110100111111110010010000000010111001110100101000111010000100110101000011010100010111011100001101101110000111001010011110111110101101001110010101000001000100000101101001011000110000111001100100001011111000000110111100110000101010101001 :
b1 8
b10 =
1#
1+
#170000
0#
0+
#175000
b11 -
1,
b100101110110100101100010101100110000011100001111001110001010001000000000000000000000000000000000000000000000000000000000000000000000000000000000000000000000000000000000000000000000000000000000000000000000000000000000000000000000000000000000000000000000000000000000000000000000000000000000000000000000000000000000000000000000000000000000000000000000000000000000000000000000000000000000000000000000000000000000000000000000000000000000000000000000000 4
b10 8
17
b11010011001101001000110101010010100011000101100110110110100111100 *
b1001011101101001011000101011001100000111000011110011100010100010000000000000000000000000000000000000000000000000000000000000000000000000000000000000000000000000000000000000000000000000000000000000000000000000000000000000000000000000000000000000000000000000000000000000000000000000000000000000000000000000000000000000000000000000000000000000000000000000000000000000000000000000000000000000000000000000000000000000000000000000000000000000000000000000000000000000000000000000000000000000000000000000000000000000000 <
b1101001011101101001011000101011001100000111000011110011100010100010000000000000000000000000000000000000000000000000000000000000000000000000000000000000000000000000000000000000000000000000000000000000000000000000000000000000000000000000000000000000000000000000000000000000000000000000000000000000000000000000000000000000000000000000000000000000000000000000000000000000000000000000000000000000000000000000000000000000000000000000000000000000000000000000000000000000000000000000000000000000000000000000000000000000000 "
b1101001011101101001011000101011001100000111000011110011100010100010000000000000000000000000000000000000000000000000000000000000000000000000000000000000000000000000000000000000000000000000000000000000000000000000000000000000000000000000000000000000000000000000000000000000000000000000000000000000000000000000000000000000000000000000000000000000000000000000000000000000000000000000000000000000000000000000000000000000000000000000000000000000000000000000000000000000000000000000000000000000000000000000000000000000000 3
b1111001100001010101000001000111110000001101100000000101000011110111010011110011111010011101011110111110011000000000111011011101010000001100000110111111000101110101001001010100110101101100111111110101000010100001101000011110110111011110110010101111010110010101001101100010001001010111011110000100000001101001111011100100000111110111111101011010111100100011101000110100110011010101010011101101111101101001011110101011011000100101000100110011110010110 ;
b1101011111011100010110100001011000100001100011110111000101000101011001011011110001111010100000111110101000100000111001001100000011101100101101111111100000100010011011101001110110101110011111111101101011101010101101010001011111010100010001001001110000100110100010101111000010100011010011111111001001000000001011100111010010100011101000010011010100001101010001011101110000110110111000011100101001111011111010110100111001010100000100010000010110100101 :
1#
1+
#180000
0#
0+
#185000
b1010011001101001000110101010010100011000101100110110110100111100010010111011010010110001010110011000001110000111100111000101000100000000000000000000000000000000000000000000000000000000000000000000000000000000000000000000000000000000000000000000000000000000000000000000000000000000000000000000000000000000000000000000000000000000000000000000000000000000000000000000000000000000000000000000000000000000000000000000000000000000000000000000000000000000 4
b1110001010011111111010101111000110111010010001011101000110001011 *
b10100110011010010001101010100101000110001011001101101101001111000100101110110100101100010101100110000011100001111001110001010001000000000000000000000000000000000000000000000000000000000000000000000000000000000000000000000000000000000000000000000000000000000000000000000000000000000000000000000000000000000000000000000000000000000000000000000000000000000000000000000000000000000000000000000000000000000000000000000000000000000000000000000000000000000000000000000000000000000000000000000000000000000000000000000000 <
b1110100110011010010001101010100101000110001011001101101101001111000100101110110100101100010101100110000011100001111001110001010001000000000000000000000000000000000000000000000000000000000000000000000000000000000000000000000000000000000000000000000000000000000000000000000000000000000000000000000000000000000000000000000000000000000000000000000000000000000000000000000000000000000000000000000000000000000000000000000000000000000000000000000000000000000000000000000000000000000000000000000000000000000000000000000000 "
b1110100110011010010001101010100101000110001011001101101101001111000100101110110100101100010101100110000011100001111001110001010001000000000000000000000000000000000000000000000000000000000000000000000000000000000000000000000000000000000000000000000000000000000000000000000000000000000000000000000000000000000000000000000000000000000000000000000000000000000000000000000000000000000000000000000000000000000000000000000000000000000000000000000000000000000000000000000000000000000000000000000000000000000000000000000000 3
b111100110000101010100000100011111000000110110000000010100001111011101001111001111101001110101111011111001100000000011101101110101000000110000011011111100010111010100100101010011010110110011111111010100001010000110100001111011011101111011001010111101011001010100110110001000100101011101111000010000000110100111101110010000011111011111110101101011110010001110100011010011001101010101001 ;
b110101111101110001011010000101100010000110001111011100010100010101100101101111000111101010000011111010100010000011100100110000001110110010110111111110000010001001101110100111011010111001111111110110101110101010110101000101111101010001000100100111000010011010001010111100001010001101001111111100100100000000101110011101001010001110100001001101010000110101000101110111000011011011100001 :
b11 8
1#
1+
#190000
0#
0+
#195000
b10 -
0,
b1110001010011111111010101111000110111010010001011101000110001011101001100110100100011010101001010001100010110011011011010011110001001011101101001011000101011001100000111000011110011100010100010000000000000000000000000000000000000000000000000000000000000000000000000000000000000000000000000000000000000000000000000000000000000000000000000000000000000000000000000000000000000000000000000000000000000000000000000000000000000000000000000000000000000000 4
b100 8
07
b10011000110110100111011100011111011111010010011010110110000111100 *
b11100010100111111110101011110001101110100100010111010001100010111010011001101001000110101010010100011000101100110110110100111100010010111011010010110001010110011000001110000111100111000101000100000000000000000000000000000000000000000000000000000000000000000000000000000000000000000000000000000000000000000000000000000000000000000000000000000000000000000000000000000000000000000000000000000000000000000000000000000000000000000000000000000000000000000000000000000000000000000000000000000000000000000000000000000000 <
b1011100010100111111110101011110001101110100100010111010001100010111010011001101001000110101010010100011000101100110110110100111100010010111011010010110001010110011000001110000111100111000101000100000000000000000000000000000000000000000000000000000000000000000000000000000000000000000000000000000000000000000000000000000000000000000000000000000000000000000000000000000000000000000000000000000000000000000000000000000000000000000000000000000000000000000000000000000000000000000000000000000000000000000000000000000000 "
b1011100010100111111110101011110001101110100100010111010001100010111010011001101001000110101010010100011000101100110110110100111100010010111011010010110001010110011000001110000111100111000101000100000000000000000000000000000000000000000000000000000000000000000000000000000000000000000000000000000000000000000000000000000000000000000000000000000000000000000000000000000000000000000000000000000000000000000000000000000000000000000000000000000000000000000000000000000000000000000000000000000000000000000000000000000000 3
b11110011000010101010000010001111100000011011000000001010000111101110100111100111110100111010111101111100110000000001110110111010100000011000001101111110001011101010010010101001101011011001111111101010000101000011010000111101101110111101100101011110101100101010011011000100010010101110111100001000000011010011110111001000 ;
b11010111110111000101101000010110001000011000111101110001010001010110010110111100011110101000001111101010001000001110010011000000111011001011011111111000001000100110111010011101101011100111111111011010111010101011010100010111110101000100010010011100001001101000101011110000101000110100111111110010010000000010111001110100 :
1#
1+
#200000
0#
0+
#205000
b11 -
1,
b11000110110100111011100011111011111010010011010110110000111100111000101001111111101010111100011011101001000101110100011000101110100110011010010001101010100101000110001011001101101101001111000100101110110100101100010101100110000011100001111001110001010001000000000000000000000000000000000000000000000000000000000000000000000000000000000000000000000000000000000000000000000000000000000000000000000000000000000000000000000000000000000000000000000000 4
17
b11100010011111110111010010101010110010000000111011111101011011001 *
b110001101101001110111000111110111110100100110101101100001111001110001010011111111010101111000110111010010001011101000110001011101001100110100100011010101001010001100010110011011011010011110001001011101101001011000101011001100000111000011110011100010100010000000000000000000000000000000000000000000000000000000000000000000000000000000000000000000000000000000000000000000000000000000000000000000000000000000000000000000000000000000000000000000000000000000000000000000000000000000000000000000000000000000000000000 <
b1100110001101101001110111000111110111110100100110101101100001111001110001010011111111010101111000110111010010001011101000110001011101001100110100100011010101001010001100010110011011011010011110001001011101101001011000101011001100000111000011110011100010100010000000000000000000000000000000000000000000000000000000000000000000000000000000000000000000000000000000000000000000000000000000000000000000000000000000000000000000000000000000000000000000000000000000000000000000000000000000000000000000000000000000000000000 "
b1100110001101101001110111000111110111110100100110101101100001111001110001010011111111010101111000110111010010001011101000110001011101001100110100100011010101001010001100010110011011011010011110001001011101101001011000101011001100000111000011110011100010100010000000000000000000000000000000000000000000000000000000000000000000000000000000000000000000000000000000000000000000000000000000000000000000000000000000000000000000000000000000000000000000000000000000000000000000000000000000000000000000000000000000000000000 3
b1111001100001010101000001000111110000001101100000000101000011110111010011110011111010011101011110111110011000000000111011011101010000001100000110111111000101110101001001010100110101101100111111110101000010100001101000011110110111011110110010101111010110010 ;
b1101011111011100010110100001011000100001100011110111000101000101011001011011110001111010100000111110101000100000111001001100000011101100101101111111100000100010011011101001110110101110011111111101101011101010101101010001011111010100010001001001110000100110 :
b101 8
1#
1+
#210000
0#
0+
#215000
b1100010011111110111010010101010110010000000111011111101011011001001100011011010011101110001111101111101001001101011011000011110011100010100111111110101011110001101110100100010111010001100010111010011001101001000110101010010100011000101100110110110100111100010010111011010010110001010110011000001110000111100111000101000100000000000000000000000000000000000000000000000000000000000000000000000000000000000000000000000000000000000000000000000000000000 4
b10110111000111011011101100101000100010011010001110101110000011111 *
b110 8
b11000100111111101110100101010101100100000001110111111010110110010011000110110100111011100011111011111010010011010110110000111100111000101001111111101010111100011011101001000101110100011000101110100110011010010001101010100101000110001011001101101101001111000100101110110100101100010101100110000011100001111001110001010001000000000000000000000000000000000000000000000000000000000000000000000000000000000000000000000000000000000000000000000000000000000000000000000000000000000000000000000000000000000000000000000000 <
b1111000100111111101110100101010101100100000001110111111010110110010011000110110100111011100011111011111010010011010110110000111100111000101001111111101010111100011011101001000101110100011000101110100110011010010001101010100101000110001011001101101101001111000100101110110100101100010101100110000011100001111001110001010001000000000000000000000000000000000000000000000000000000000000000000000000000000000000000000000000000000000000000000000000000000000000000000000000000000000000000000000000000000000000000000000000 "
b1111000100111111101110100101010101100100000001110111111010110110010011000110110100111011100011111011111010010011010110110000111100111000101001111111101010111100011011101001000101110100011000101110100110011010010001101010100101000110001011001101101101001111000100101110110100101100010101100110000011100001111001110001010001000000000000000000000000000000000000000000000000000000000000000000000000000000000000000000000000000000000000000000000000000000000000000000000000000000000000000000000000000000000000000000000000 3
b111100110000101010100000100011111000000110110000000010100001111011101001111001111101001110101111011111001100000000011101101110101000000110000011011111100010111010100100101010011010110110011111 ;
b110101111101110001011010000101100010000110001111011100010100010101100101101111000111101010000011111010100010000011100100110000001110110010110111111110000010001001101110100111011010111001111111 :
1#
1+
#220000
0#
0+
