hardware/RTL/adder.v
`timescale 1ns / 1ps

module adder #(parameter ADDER_SIZE=4)(
    input  wire         clk,
    input  wire         resetn,
    input  wire         start,
    input  wire         subtract,
    input  wire [512:0] in_a,
    input  wire [512:0] in_b,    
    output wire [513:0] result,
    output wire         done    
    );
    localparam [2:0]    STATE_IDLE  = 3'b000,//waiting for start
                        STATE_ONE   = 3'b001,//load inputs
                        STATE_TWO   = 3'b010,//load addition result to output register 
                        STATE_THREE = 3'b011,//load shifted version to output register 
                        STATE_FOUR  = 3'b100;//done   
    reg [511:0] reg_result;
    reg [511:0] operand_a;
    reg [511:0] operand_b;
    wire [ADDER_SIZE:0] add_result;

    wire mux_sel;
    wire mux_sel_result;
    assign mux_sel=(state==STATE_ONE) ? 1'b1:1'b0;// 1 selects input 0 selects shifted

    assign done=(state==STATE_FOUR) ? 1'b1 :1'b0;// 1 selects shifted resuld 0 selects add result
    assign mux_sel_result=(state==STATE_THREE) ? 1'b1:1'b0;
    wire [1:0]hack;
    assign hack=in_a[512]+in_b[512]+carry; 
    reg carry;
    always @(posedge clk) begin
        if (resetn==1'b0 )begin
            reg_result <= 0;
	    operand_a <=0;
            operand_b <=0;
            carry <=0;
        end
        else begin
            operand_a<= (mux_sel==1'b1)? in_a:((mux_sel_result==1'b1)? operand_a:(operand_a>>ADDER_SIZE)); 		
            operand_b<= (mux_sel==1'b1)? in_b:((mux_sel_result==1'b1)? operand_b:(operand_b>>ADDER_SIZE)); 
            reg_result<= (mux_sel_result==1'b0)? ({add_result[ADDER_SIZE-1:0],reg_result[(512-ADDER_SIZE)-1:0]}):(reg_result>>ADDER_SIZE);
            carry <= (mux_sel_result==1'b0)? add_result[ADDER_SIZE]:carry;
	    if(state==STATE_FOUR)
	    	$display("result %0x ",result);
        end
    end  		
    assign result = {hack[1:0],reg_result};
    assign add_result = (mux_sel_result==1'b0)?( operand_a[ADDER_SIZE-1:0]+operand_b[ADDER_SIZE-1:0]+carry):add_result;//save power

                    
    reg  [7:0] cnt;         //3-bit register
    reg  [2:0] state;       //3-bit register
    reg  [2:0] next_state;  //3-bit wire
                        //Sequential Counter logi
    always @(posedge clk)    begin
	if(next_state>=STATE_TWO && next_state<=STATE_THREE)
            begin
                   cnt <= cnt +1;
            end
	else
		cnt <= 0;
    end 
    
    always @(*) 
             begin
                  case (state)
                       STATE_IDLE:
                           begin
                               next_state <= (start==1'b1) ? STATE_ONE:STATE_IDLE;
                           end
                       STATE_ONE:
                           begin
                               next_state <= STATE_TWO;
                           end
                       STATE_TWO:
                            begin
                                next_state <= (cnt<((512/ADDER_SIZE)*2-1))?  STATE_THREE:STATE_FOUR;//?latch 
                            end
                       STATE_THREE:
                            begin
                                next_state <=  STATE_TWO; 
                            end
                       STATE_FOUR: 
                           begin
                                next_state <= STATE_IDLE;
                           end
                       default: 
                           begin
                              next_state <= STATE_IDLE;
                           end
                  endcase
             end                             
    
       //Synchronous logic to update state
     always @(posedge clk)
     begin
         if (resetn==1'b0)
         begin
             state <= 0;
         end
         else
         begin
             state <= next_state;
         end
     end
     
 
endmodule

hardware/tb/tb_adder.v

`timescale 1ns / 1ps

/*
Assignment:
1. Use this testbench (tb) to verify the correctness of your adder
    You can start the simulation by pressing the buttons on the left-hand: Simulation | Run Simulation
2. Implement a multi-precision adder in adder.v
3. Update the design with a two's-compliment subtractor (activate it with the 'subtract' wire)
3. Make an implementation of your design (Implementation | Run Implementation).
4. Determine the maximum clock frequency of the design (Efficient designs have a clock of around 100MHz)
5. Calculate the total execution time of one add operation
*/

`timescale 1ns / 1ps
`include "RTL/adder.v"
`define RESET_TIME 25
`define CLK_PERIOD 10
`define CLK_HALF 5

module tb_adder();

    reg          clk;
    reg          resetn;
    reg  [512:0] in_a;
    reg  [512:0] in_b;
    reg          start;
    reg          subtract;
    reg          result_ok;
    wire [513:0] result;
    wire         done;

    adder dut (
        .clk      (clk     ),
        .resetn   (resetn  ),
        .start    (start   ),
        .subtract (subtract),
        .in_a     (in_a    ),
        .in_b     (in_b    ),
        .result   (result  ),
        .done     (done    ));

    // Generate Clock
    initial begin
        clk = 0;
        forever #`CLK_HALF clk = ~clk;
    end

    // Initialize signals to zero
    initial begin
        in_a <= 0;
        in_b <= 0;
        subtract <= 0;
        start <= 0;
    end

    // Reset the circuit
    initial begin
        resetn = 0;
        #`RESET_TIME
        resetn = 1;
    end

    task perform_add;
        input [512:0] a;
        input [512:0] b;
        begin
            in_a <= a;
            in_b <= b;
            start <= 1'd1;
            subtract <= 1'd0;
            #`CLK_PERIOD;
            start <= 1'd0;
            wait (done==1);
            #`CLK_PERIOD;
        end
    endtask

    task perform_sub;
        input [512:0] a;
        input [512:0] b;
        begin
            in_a <= a;
            in_b <= b;
            start <= 1'd1;
            subtract <= 1'd1;
            #`CLK_PERIOD;
            start <= 1'd0;
            wait (done==1);
            #`CLK_PERIOD;
        end
    endtask

    initial begin
    $dumpfile("adder.vcd");
    $dumpvars;
    #`RESET_TIME

    /*************TEST ADDITION*************/
    // Check if 1+1=2
    #`CLK_PERIOD;
    perform_add(513'h1, 513'h1);
    wait (done==1);
    result_ok = (result==514'h2);

    $display("result=",result_ok);
    //Test addition with large test vectors. You can generate your own with the magma online calculator
    perform_add(513'h1d7dc5a16218f714565bc7a83ea20e4c0ecb7f8226e9dae7fdaeab517d4449c268af0a34ff2402e74a3a1350d45dc36e1ca7beb4e541105a58c3990be06f30aa9,
                513'h1f30aa08f81b00a1ee9e7d3af7cc01dba81837e2ea4a9ad9fea14343dbbd95eb2a6c44aef080d3dc83efeb5e474699aa9dbed2f56c4a26796bf7b209b7c9491a8);
    wait (done==1);//this is a TRAP, don't use for debug 
     result_ok = (result==514'h3cae6faa5a33f7b644fa44e3366e1027b6e3b765113475c1fc4fee955901dfad931b4ee3efa4d6c3ce29feaf1ba45d18ba6691aa518b36d3c4bb4b15983879c51);
    $display("result=",result_ok);
#1300;/*

    /*************TEST SUBTRACTION*************/
    //Check if 1-1=0
/*    #`CLK_PERIOD;
    #`CLK_PERIOD;
    #`CLK_PERIOD;
    perform_sub(513'h1, 513'h1);
    wait (done==1);
    result_ok = (result==514'h0);

    //Test subtraction with large test vectors. You can generate your own with the magma online calculator
    perform_sub(513'h17fcaaf8fe3fd0ee41050d74d78c6087b359fc7813e749a65c4981218f36b4da932ce6e09aa0d31ad9fdddd3abd5114a71b7fd733bbca0f2261ddb7d286cf6ee1,
                513'h1f9a0c360f98cb4e0bdac0d74ee9af59daada1a769b5b2b91a54bb6a5790da2da28b78cc2d14a3f513da8adaef1e148e3a9eaecc4ca7a211bed70da87129fb6c6);
    wait (done==1);
    result_ok = (result==514'h78629ec2eea705a0352a4c9d88a2b12dd8ac5ad0aa3196ed41f4c5b737a5daacf0a16e146d8c2f25c62352f8bcb6fcbc37194ea6ef14fee06746cdd4b742fb81b);
    $display("result=%x",result);
  */  
    $finish;

    end

endmodule

hardware/adder.vcd
$date
	Mon Oct 16 22:45:21 2017
$end
$version
	Icarus Verilog
$end
$timescale
	1ps
$end
$scope module tb_adder $end
$var wire 1 ! done $end
$var wire 514 " result [513:0] $end
$var reg 1 # clk $end
$var reg 513 $ in_a [512:0] $end
$var reg 513 % in_b [512:0] $end
$var reg 1 & resetn $end
$var reg 1 ' result_ok $end
$var reg 1 ( start $end
$var reg 1 ) subtract $end
$scope module dut $end
$var wire 5 * add_result [4:0] $end
$var wire 1 + clk $end
$var wire 1 ! done $end
$var wire 2 , hack [1:0] $end
$var wire 513 - in_a [512:0] $end
$var wire 513 . in_b [512:0] $end
$var wire 1 / mux_sel $end
$var wire 1 0 mux_sel_result $end
$var wire 1 1 resetn $end
$var wire 514 2 result [513:0] $end
$var wire 1 3 start $end
$var wire 1 4 subtract $end
$var reg 1 5 carry $end
$var reg 8 6 cnt [7:0] $end
$var reg 3 7 next_state [2:0] $end
$var reg 512 8 operand_a [511:0] $end
$var reg 512 9 operand_b [511:0] $end
$var reg 512 : reg_result [511:0] $end
$var reg 3 ; state [2:0] $end
$upscope $end
$scope task perform_add $end
$var reg 513 < a [512:0] $end
$var reg 513 = b [512:0] $end
$upscope $end
$scope task perform_sub $end
$var reg 513 > a [512:0] $end
$var reg 513 ? b [512:0] $end
$upscope $end
$upscope $end
$enddefinitions $end
#0
$dumpvars
bx ?
bx >
bx =
bx <
bx ;
bx :
bx 9
bx 8
b0 7
bx 6
x5
04
03
bx 2
01
x0
x/
b0 .
b0 -
bx ,
0+
bx *
0)
0(
x'
0&
b0 %
b0 $
0#
bx "
x!
$end
#5000
b0 *
0/
0!
00
05
b0 ,
b0 9
b0 8
b0 :
b0 "
b0 2
b0 6
b0 ;
1#
1+
#10000
0#
0+
#15000
1#
1+
#20000
0#
0+
#25000
1#
1+
1&
11
#30000
0#
0+
#35000
b1 7
1(
13
b1 %
b1 .
b1 $
b1 -
1#
1+
b1 =
b1 <
#40000
0#
0+
#45000
b10 7
1/
b1 ;
0(
03
1#
1+
#50000
0#
0+
#55000
b11 7
b10 *
0/
b10 ;
b1 6
b1 9
b1 8
1#
1+
#60000
0#
0+
#65000
b10 7
10
b100000000000000000000000000000000000000000000000000000000000000000000000000000000000000000000000000000000000000000000000000000000000000000000000000000000000000000000000000000000000000000000000000000000000000000000000000000000000000000000000000000000000000000000000000000000000000000000000000000000000000000000000000000000000000000000000000000000000000000000000000000000000000000000000000000000000000000000000000000000000000000000000000000000000000000000000000000000000000000000000000000000000000000000000000000 :
b100000000000000000000000000000000000000000000000000000000000000000000000000000000000000000000000000000000000000000000000000000000000000000000000000000000000000000000000000000000000000000000000000000000000000000000000000000000000000000000000000000000000000000000000000000000000000000000000000000000000000000000000000000000000000000000000000000000000000000000000000000000000000000000000000000000000000000000000000000000000000000000000000000000000000000000000000000000000000000000000000000000000000000000000000000 "
b100000000000000000000000000000000000000000000000000000000000000000000000000000000000000000000000000000000000000000000000000000000000000000000000000000000000000000000000000000000000000000000000000000000000000000000000000000000000000000000000000000000000000000000000000000000000000000000000000000000000000000000000000000000000000000000000000000000000000000000000000000000000000000000000000000000000000000000000000000000000000000000000000000000000000000000000000000000000000000000000000000000000000000000000000000 2
b0 9
b0 8
b10 6
b11 ;
1#
1+
#70000
0#
0+
#75000
b11 7
b0 *
00
b10 ;
b11 6
b10000000000000000000000000000000000000000000000000000000000000000000000000000000000000000000000000000000000000000000000000000000000000000000000000000000000000000000000000000000000000000000000000000000000000000000000000000000000000000000000000000000000000000000000000000000000000000000000000000000000000000000000000000000000000000000000000000000000000000000000000000000000000000000000000000000000000000000000000000000000000000000000000000000000000000000000000000000000000000000000000000000000000000000000000 :
b10000000000000000000000000000000000000000000000000000000000000000000000000000000000000000000000000000000000000000000000000000000000000000000000000000000000000000000000000000000000000000000000000000000000000000000000000000000000000000000000000000000000000000000000000000000000000000000000000000000000000000000000000000000000000000000000000000000000000000000000000000000000000000000000000000000000000000000000000000000000000000000000000000000000000000000000000000000000000000000000000000000000000000000000000 "
b10000000000000000000000000000000000000000000000000000000000000000000000000000000000000000000000000000000000000000000000000000000000000000000000000000000000000000000000000000000000000000000000000000000000000000000000000000000000000000000000000000000000000000000000000000000000000000000000000000000000000000000000000000000000000000000000000000000000000000000000000000000000000000000000000000000000000000000000000000000000000000000000000000000000000000000000000000000000000000000000000000000000000000000000000 2
1#
1+
#80000
0#
0+
#85000
b10 7
10
b100 6
b11 ;
1#
1+
#90000
0#
0+
#95000
b11 7
00
b10 ;
b101 6
b1000000000000000000000000000000000000000000000000000000000000000000000000000000000000000000000000000000000000000000000000000000000000000000000000000000000000000000000000000000000000000000000000000000000000000000000000000000000000000000000000000000000000000000000000000000000000000000000000000000000000000000000000000000000000000000000000000000000000000000000000000000000000000000000000000000000000000000000000000000000000000000000000000000000000000000000000000000000000000000000000000000000000000000000 :
b1000000000000000000000000000000000000000000000000000000000000000000000000000000000000000000000000000000000000000000000000000000000000000000000000000000000000000000000000000000000000000000000000000000000000000000000000000000000000000000000000000000000000000000000000000000000000000000000000000000000000000000000000000000000000000000000000000000000000000000000000000000000000000000000000000000000000000000000000000000000000000000000000000000000000000000000000000000000000000000000000000000000000000000000 "
b1000000000000000000000000000000000000000000000000000000000000000000000000000000000000000000000000000000000000000000000000000000000000000000000000000000000000000000000000000000000000000000000000000000000000000000000000000000000000000000000000000000000000000000000000000000000000000000000000000000000000000000000000000000000000000000000000000000000000000000000000000000000000000000000000000000000000000000000000000000000000000000000000000000000000000000000000000000000000000000000000000000000000000000000 2
1#
1+
#100000
0#
0+
#105000
b10 7
10
b110 6
b11 ;
1#
1+
#110000
0#
0+
#115000
b11 7
00
b10 ;
b111 6
b100000000000000000000000000000000000000000000000000000000000000000000000000000000000000000000000000000000000000000000000000000000000000000000000000000000000000000000000000000000000000000000000000000000000000000000000000000000000000000000000000000000000000000000000000000000000000000000000000000000000000000000000000000000000000000000000000000000000000000000000000000000000000000000000000000000000000000000000000000000000000000000000000000000000000000000000000000000000000000000000000000000000000000 :
b100000000000000000000000000000000000000000000000000000000000000000000000000000000000000000000000000000000000000000000000000000000000000000000000000000000000000000000000000000000000000000000000000000000000000000000000000000000000000000000000000000000000000000000000000000000000000000000000000000000000000000000000000000000000000000000000000000000000000000000000000000000000000000000000000000000000000000000000000000000000000000000000000000000000000000000000000000000000000000000000000000000000000000 "
b100000000000000000000000000000000000000000000000000000000000000000000000000000000000000000000000000000000000000000000000000000000000000000000000000000000000000000000000000000000000000000000000000000000000000000000000000000000000000000000000000000000000000000000000000000000000000000000000000000000000000000000000000000000000000000000000000000000000000000000000000000000000000000000000000000000000000000000000000000000000000000000000000000000000000000000000000000000000000000000000000000000000000000 2
1#
1+
#120000
0#
0+
#125000
b10 7
10
b1000 6
b11 ;
1#
1+
#130000
0#
0+
#135000
b11 7
00
b10 ;
b1001 6
b10000000000000000000000000000000000000000000000000000000000000000000000000000000000000000000000000000000000000000000000000000000000000000000000000000000000000000000000000000000000000000000000000000000000000000000000000000000000000000000000000000000000000000000000000000000000000000000000000000000000000000000000000000000000000000000000000000000000000000000000000000000000000000000000000000000000000000000000000000000000000000000000000000000000000000000000000000000000000000000000000000000000000 :
b10000000000000000000000000000000000000000000000000000000000000000000000000000000000000000000000000000000000000000000000000000000000000000000000000000000000000000000000000000000000000000000000000000000000000000000000000000000000000000000000000000000000000000000000000000000000000000000000000000000000000000000000000000000000000000000000000000000000000000000000000000000000000000000000000000000000000000000000000000000000000000000000000000000000000000000000000000000000000000000000000000000000000 "
b10000000000000000000000000000000000000000000000000000000000000000000000000000000000000000000000000000000000000000000000000000000000000000000000000000000000000000000000000000000000000000000000000000000000000000000000000000000000000000000000000000000000000000000000000000000000000000000000000000000000000000000000000000000000000000000000000000000000000000000000000000000000000000000000000000000000000000000000000000000000000000000000000000000000000000000000000000000000000000000000000000000000000 2
1#
1+
#140000
0#
0+
#145000
b10 7
10
b1010 6
b11 ;
1#
1+
#150000
0#
0+
#155000
b11 7
00
b10 ;
b1011 6
b1000000000000000000000000000000000000000000000000000000000000000000000000000000000000000000000000000000000000000000000000000000000000000000000000000000000000000000000000000000000000000000000000000000000000000000000000000000000000000000000000000000000000000000000000000000000000000000000000000000000000000000000000000000000000000000000000000000000000000000000000000000000000000000000000000000000000000000000000000000000000000000000000000000000000000000000000000000000000000000000000000000000 :
b1000000000000000000000000000000000000000000000000000000000000000000000000000000000000000000000000000000000000000000000000000000000000000000000000000000000000000000000000000000000000000000000000000000000000000000000000000000000000000000000000000000000000000000000000000000000000000000000000000000000000000000000000000000000000000000000000000000000000000000000000000000000000000000000000000000000000000000000000000000000000000000000000000000000000000000000000000000000000000000000000000000000 "
b1000000000000000000000000000000000000000000000000000000000000000000000000000000000000000000000000000000000000000000000000000000000000000000000000000000000000000000000000000000000000000000000000000000000000000000000000000000000000000000000000000000000000000000000000000000000000000000000000000000000000000000000000000000000000000000000000000000000000000000000000000000000000000000000000000000000000000000000000000000000000000000000000000000000000000000000000000000000000000000000000000000000 2
1#
1+
#160000
0#
0+
#165000
b10 7
10
b1100 6
b11 ;
1#
1+
#170000
0#
0+
#175000
b11 7
00
b10 ;
b1101 6
b100000000000000000000000000000000000000000000000000000000000000000000000000000000000000000000000000000000000000000000000000000000000000000000000000000000000000000000000000000000000000000000000000000000000000000000000000000000000000000000000000000000000000000000000000000000000000000000000000000000000000000000000000000000000000000000000000000000000000000000000000000000000000000000000000000000000000000000000000000000000000000000000000000000000000000000000000000000000000000000000000000 :
b100000000000000000000000000000000000000000000000000000000000000000000000000000000000000000000000000000000000000000000000000000000000000000000000000000000000000000000000000000000000000000000000000000000000000000000000000000000000000000000000000000000000000000000000000000000000000000000000000000000000000000000000000000000000000000000000000000000000000000000000000000000000000000000000000000000000000000000000000000000000000000000000000000000000000000000000000000000000000000000000000000 "
b100000000000000000000000000000000000000000000000000000000000000000000000000000000000000000000000000000000000000000000000000000000000000000000000000000000000000000000000000000000000000000000000000000000000000000000000000000000000000000000000000000000000000000000000000000000000000000000000000000000000000000000000000000000000000000000000000000000000000000000000000000000000000000000000000000000000000000000000000000000000000000000000000000000000000000000000000000000000000000000000000000 2
1#
1+
#180000
0#
0+
#185000
b10 7
10
b1110 6
b11 ;
1#
1+
#190000
0#
0+
#195000
b11 7
00
b10 ;
b1111 6
b10000000000000000000000000000000000000000000000000000000000000000000000000000000000000000000000000000000000000000000000000000000000000000000000000000000000000000000000000000000000000000000000000000000000000000000000000000000000000000000000000000000000000000000000000000000000000000000000000000000000000000000000000000000000000000000000000000000000000000000000000000000000000000000000000000000000000000000000000000000000000000000000000000000000000000000000000000000000000000000000000 :
b10000000000000000000000000000000000000000000000000000000000000000000000000000000000000000000000000000000000000000000000000000000000000000000000000000000000000000000000000000000000000000000000000000000000000000000000000000000000000000000000000000000000000000000000000000000000000000000000000000000000000000000000000000000000000000000000000000000000000000000000000000000000000000000000000000000000000000000000000000000000000000000000000000000000000000000000000000000000000000000000000 "
b10000000000000000000000000000000000000000000000000000000000000000000000000000000000000000000000000000000000000000000000000000000000000000000000000000000000000000000000000000000000000000000000000000000000000000000000000000000000000000000000000000000000000000000000000000000000000000000000000000000000000000000000000000000000000000000000000000000000000000000000000000000000000000000000000000000000000000000000000000000000000000000000000000000000000000000000000000000000000000000000000 2
1#
1+
#200000
0#
0+
#205000
b10 7
10
b10000 6
b11 ;
1#
1+
#210000
0#
0+
#215000
b11 7
00
b10 ;
b10001 6
b1000000000000000000000000000000000000000000000000000000000000000000000000000000000000000000000000000000000000000000000000000000000000000000000000000000000000000000000000000000000000000000000000000000000000000000000000000000000000000000000000000000000000000000000000000000000000000000000000000000000000000000000000000000000000000000000000000000000000000000000000000000000000000000000000000000000000000000000000000000000000000000000000000000000000000000000000000000000000000000000 :
b1000000000000000000000000000000000000000000000000000000000000000000000000000000000000000000000000000000000000000000000000000000000000000000000000000000000000000000000000000000000000000000000000000000000000000000000000000000000000000000000000000000000000000000000000000000000000000000000000000000000000000000000000000000000000000000000000000000000000000000000000000000000000000000000000000000000000000000000000000000000000000000000000000000000000000000000000000000000000000000000 "
b1000000000000000000000000000000000000000000000000000000000000000000000000000000000000000000000000000000000000000000000000000000000000000000000000000000000000000000000000000000000000000000000000000000000000000000000000000000000000000000000000000000000000000000000000000000000000000000000000000000000000000000000000000000000000000000000000000000000000000000000000000000000000000000000000000000000000000000000000000000000000000000000000000000000000000000000000000000000000000000000 2
1#
1+
#220000
0#
0+
#225000
b10 7
10
b10010 6
b11 ;
1#
1+
#230000
0#
0+
#235000
b11 7
00
b10 ;
b10011 6
b100000000000000000000000000000000000000000000000000000000000000000000000000000000000000000000000000000000000000000000000000000000000000000000000000000000000000000000000000000000000000000000000000000000000000000000000000000000000000000000000000000000000000000000000000000000000000000000000000000000000000000000000000000000000000000000000000000000000000000000000000000000000000000000000000000000000000000000000000000000000000000000000000000000000000000000000000000000000000000 :
b100000000000000000000000000000000000000000000000000000000000000000000000000000000000000000000000000000000000000000000000000000000000000000000000000000000000000000000000000000000000000000000000000000000000000000000000000000000000000000000000000000000000000000000000000000000000000000000000000000000000000000000000000000000000000000000000000000000000000000000000000000000000000000000000000000000000000000000000000000000000000000000000000000000000000000000000000000000000000000 "
b100000000000000000000000000000000000000000000000000000000000000000000000000000000000000000000000000000000000000000000000000000000000000000000000000000000000000000000000000000000000000000000000000000000000000000000000000000000000000000000000000000000000000000000000000000000000000000000000000000000000000000000000000000000000000000000000000000000000000000000000000000000000000000000000000000000000000000000000000000000000000000000000000000000000000000000000000000000000000000 2
1#
1+
#240000
0#
0+
#245000
b10 7
10
b10100 6
b11 ;
1#
1+
#250000
0#
0+
#255000
b11 7
00
b10 ;
b10101 6
b10000000000000000000000000000000000000000000000000000000000000000000000000000000000000000000000000000000000000000000000000000000000000000000000000000000000000000000000000000000000000000000000000000000000000000000000000000000000000000000000000000000000000000000000000000000000000000000000000000000000000000000000000000000000000000000000000000000000000000000000000000000000000000000000000000000000000000000000000000000000000000000000000000000000000000000000000000000000000 :
b10000000000000000000000000000000000000000000000000000000000000000000000000000000000000000000000000000000000000000000000000000000000000000000000000000000000000000000000000000000000000000000000000000000000000000000000000000000000000000000000000000000000000000000000000000000000000000000000000000000000000000000000000000000000000000000000000000000000000000000000000000000000000000000000000000000000000000000000000000000000000000000000000000000000000000000000000000000000000 "
b10000000000000000000000000000000000000000000000000000000000000000000000000000000000000000000000000000000000000000000000000000000000000000000000000000000000000000000000000000000000000000000000000000000000000000000000000000000000000000000000000000000000000000000000000000000000000000000000000000000000000000000000000000000000000000000000000000000000000000000000000000000000000000000000000000000000000000000000000000000000000000000000000000000000000000000000000000000000000 2
1#
1+
#260000
0#
0+
#265000
b10 7
10
b10110 6
b11 ;
1#
1+
#270000
0#
0+
#275000
b11 7
00
b10 ;
b10111 6
b1000000000000000000000000000000000000000000000000000000000000000000000000000000000000000000000000000000000000000000000000000000000000000000000000000000000000000000000000000000000000000000000000000000000000000000000000000000000000000000000000000000000000000000000000000000000000000000000000000000000000000000000000000000000000000000000000000000000000000000000000000000000000000000000000000000000000000000000000000000000000000000000000000000000000000000000000000000000 :
b1000000000000000000000000000000000000000000000000000000000000000000000000000000000000000000000000000000000000000000000000000000000000000000000000000000000000000000000000000000000000000000000000000000000000000000000000000000000000000000000000000000000000000000000000000000000000000000000000000000000000000000000000000000000000000000000000000000000000000000000000000000000000000000000000000000000000000000000000000000000000000000000000000000000000000000000000000000000 "
b1000000000000000000000000000000000000000000000000000000000000000000000000000000000000000000000000000000000000000000000000000000000000000000000000000000000000000000000000000000000000000000000000000000000000000000000000000000000000000000000000000000000000000000000000000000000000000000000000000000000000000000000000000000000000000000000000000000000000000000000000000000000000000000000000000000000000000000000000000000000000000000000000000000000000000000000000000000000 2
1#
1+
#280000
0#
0+
#285000
b10 7
10
b11000 6
b11 ;
1#
1+
#290000
0#
0+
#295000
b11 7
00
b10 ;
b11001 6
b100000000000000000000000000000000000000000000000000000000000000000000000000000000000000000000000000000000000000000000000000000000000000000000000000000000000000000000000000000000000000000000000000000000000000000000000000000000000000000000000000000000000000000000000000000000000000000000000000000000000000000000000000000000000000000000000000000000000000000000000000000000000000000000000000000000000000000000000000000000000000000000000000000000000000000000000000000 :
b100000000000000000000000000000000000000000000000000000000000000000000000000000000000000000000000000000000000000000000000000000000000000000000000000000000000000000000000000000000000000000000000000000000000000000000000000000000000000000000000000000000000000000000000000000000000000000000000000000000000000000000000000000000000000000000000000000000000000000000000000000000000000000000000000000000000000000000000000000000000000000000000000000000000000000000000000000 "
b100000000000000000000000000000000000000000000000000000000000000000000000000000000000000000000000000000000000000000000000000000000000000000000000000000000000000000000000000000000000000000000000000000000000000000000000000000000000000000000000000000000000000000000000000000000000000000000000000000000000000000000000000000000000000000000000000000000000000000000000000000000000000000000000000000000000000000000000000000000000000000000000000000000000000000000000000000 2
1#
1+
#300000
0#
0+
#305000
b10 7
10
b11010 6
b11 ;
1#
1+
#310000
0#
0+
#315000
b11 7
00
b10 ;
b11011 6
b10000000000000000000000000000000000000000000000000000000000000000000000000000000000000000000000000000000000000000000000000000000000000000000000000000000000000000000000000000000000000000000000000000000000000000000000000000000000000000000000000000000000000000000000000000000000000000000000000000000000000000000000000000000000000000000000000000000000000000000000000000000000000000000000000000000000000000000000000000000000000000000000000000000000000000000000000 :
b10000000000000000000000000000000000000000000000000000000000000000000000000000000000000000000000000000000000000000000000000000000000000000000000000000000000000000000000000000000000000000000000000000000000000000000000000000000000000000000000000000000000000000000000000000000000000000000000000000000000000000000000000000000000000000000000000000000000000000000000000000000000000000000000000000000000000000000000000000000000000000000000000000000000000000000000000 "
b10000000000000000000000000000000000000000000000000000000000000000000000000000000000000000000000000000000000000000000000000000000000000000000000000000000000000000000000000000000000000000000000000000000000000000000000000000000000000000000000000000000000000000000000000000000000000000000000000000000000000000000000000000000000000000000000000000000000000000000000000000000000000000000000000000000000000000000000000000000000000000000000000000000000000000000000000 2
1#
1+
#320000
0#
0+
#325000
b10 7
10
b11100 6
b11 ;
1#
1+
#330000
0#
0+
#335000
b11 7
00
b10 ;
b11101 6
b1000000000000000000000000000000000000000000000000000000000000000000000000000000000000000000000000000000000000000000000000000000000000000000000000000000000000000000000000000000000000000000000000000000000000000000000000000000000000000000000000000000000000000000000000000000000000000000000000000000000000000000000000000000000000000000000000000000000000000000000000000000000000000000000000000000000000000000000000000000000000000000000000000000000000000000000 :
b1000000000000000000000000000000000000000000000000000000000000000000000000000000000000000000000000000000000000000000000000000000000000000000000000000000000000000000000000000000000000000000000000000000000000000000000000000000000000000000000000000000000000000000000000000000000000000000000000000000000000000000000000000000000000000000000000000000000000000000000000000000000000000000000000000000000000000000000000000000000000000000000000000000000000000000000 "
b1000000000000000000000000000000000000000000000000000000000000000000000000000000000000000000000000000000000000000000000000000000000000000000000000000000000000000000000000000000000000000000000000000000000000000000000000000000000000000000000000000000000000000000000000000000000000000000000000000000000000000000000000000000000000000000000000000000000000000000000000000000000000000000000000000000000000000000000000000000000000000000000000000000000000000000000 2
1#
1+
#340000
0#
0+
#345000
b10 7
10
b11110 6
b11 ;
1#
1+
#350000
0#
0+
#355000
b11 7
00
b10 ;
b11111 6
b100000000000000000000000000000000000000000000000000000000000000000000000000000000000000000000000000000000000000000000000000000000000000000000000000000000000000000000000000000000000000000000000000000000000000000000000000000000000000000000000000000000000000000000000000000000000000000000000000000000000000000000000000000000000000000000000000000000000000000000000000000000000000000000000000000000000000000000000000000000000000000000000000000000000000000 :
b100000000000000000000000000000000000000000000000000000000000000000000000000000000000000000000000000000000000000000000000000000000000000000000000000000000000000000000000000000000000000000000000000000000000000000000000000000000000000000000000000000000000000000000000000000000000000000000000000000000000000000000000000000000000000000000000000000000000000000000000000000000000000000000000000000000000000000000000000000000000000000000000000000000000000000 "
b100000000000000000000000000000000000000000000000000000000000000000000000000000000000000000000000000000000000000000000000000000000000000000000000000000000000000000000000000000000000000000000000000000000000000000000000000000000000000000000000000000000000000000000000000000000000000000000000000000000000000000000000000000000000000000000000000000000000000000000000000000000000000000000000000000000000000000000000000000000000000000000000000000000000000000 2
1#
1+
#360000
0#
0+
#365000
b10 7
10
b100000 6
b11 ;
1#
1+
#370000
0#
0+
#375000
b11 7
00
b10 ;
b100001 6
b10000000000000000000000000000000000000000000000000000000000000000000000000000000000000000000000000000000000000000000000000000000000000000000000000000000000000000000000000000000000000000000000000000000000000000000000000000000000000000000000000000000000000000000000000000000000000000000000000000000000000000000000000000000000000000000000000000000000000000000000000000000000000000000000000000000000000000000000000000000000000000000000000000000000000 :
b10000000000000000000000000000000000000000000000000000000000000000000000000000000000000000000000000000000000000000000000000000000000000000000000000000000000000000000000000000000000000000000000000000000000000000000000000000000000000000000000000000000000000000000000000000000000000000000000000000000000000000000000000000000000000000000000000000000000000000000000000000000000000000000000000000000000000000000000000000000000000000000000000000000000000 "
b10000000000000000000000000000000000000000000000000000000000000000000000000000000000000000000000000000000000000000000000000000000000000000000000000000000000000000000000000000000000000000000000000000000000000000000000000000000000000000000000000000000000000000000000000000000000000000000000000000000000000000000000000000000000000000000000000000000000000000000000000000000000000000000000000000000000000000000000000000000000000000000000000000000000000 2
1#
1+
#380000
0#
0+
#385000
b10 7
10
b100010 6
b11 ;
1#
1+
#390000
0#
0+
#395000
b11 7
00
b10 ;
b100011 6
b1000000000000000000000000000000000000000000000000000000000000000000000000000000000000000000000000000000000000000000000000000000000000000000000000000000000000000000000000000000000000000000000000000000000000000000000000000000000000000000000000000000000000000000000000000000000000000000000000000000000000000000000000000000000000000000000000000000000000000000000000000000000000000000000000000000000000000000000000000000000000000000000000000000000 :
b1000000000000000000000000000000000000000000000000000000000000000000000000000000000000000000000000000000000000000000000000000000000000000000000000000000000000000000000000000000000000000000000000000000000000000000000000000000000000000000000000000000000000000000000000000000000000000000000000000000000000000000000000000000000000000000000000000000000000000000000000000000000000000000000000000000000000000000000000000000000000000000000000000000000 "
b1000000000000000000000000000000000000000000000000000000000000000000000000000000000000000000000000000000000000000000000000000000000000000000000000000000000000000000000000000000000000000000000000000000000000000000000000000000000000000000000000000000000000000000000000000000000000000000000000000000000000000000000000000000000000000000000000000000000000000000000000000000000000000000000000000000000000000000000000000000000000000000000000000000000 2
1#
1+
#400000
0#
0+
#405000
b10 7
10
b100100 6
b11 ;
1#
1+
#410000
0#
0+
